PyTestingQA/PyTesting.py
PyTestingQA/__init__.py
PyTestingQA-2.3.1.dist-info/LICENSE
PyTestingQA-2.3.1.dist-info/METADATA
PyTestingQA-2.3.1.dist-info/WHEEL
PyTestingQA-2.3.1.dist-info/top_level.txt
PyTestingQA-2.3.1.dist-info/RECORD
